myopenpy_ltt_utils/__init__.py
myopenpy_ltt_utils/print_hi.py
myopenpy_ltt_utils-0.1.0.dist-info/METADATA
myopenpy_ltt_utils-0.1.0.dist-info/WHEEL
myopenpy_ltt_utils-0.1.0.dist-info/RECORD
