Metadata-Version: 2.1
Name: myopenpy-ltt-utils
Version: 0.1.0
Summary: just for me test
Author: Your Name
Author-email: you@example.com
Requires-Python: >=3.10,<4.0
Classifier: Programming Language :: Python :: 3
Classifier: Programming Language :: Python :: 3.10
Classifier: Programming Language :: Python :: 3.11
